pytech/django_tools/__init__.py
pytech/django_tools/decorators.py
pytech/django_tools/middlewares.py
pytech/domain/__init__.py
pytech/domain/messages.py
pytech_django_tools-2.0.1.dist-info/METADATA
pytech_django_tools-2.0.1.dist-info/WHEEL
pytech_django_tools-2.0.1.dist-info/licenses/LICENCE
pytech_django_tools-2.0.1.dist-info/RECORD
