Metadata-Version: 2.3
Name: pytech-django-tools
Version: 2.0.1
Summary: PyTech Django Tools Project
Project-URL: Homepage, https://gitlab.com/pytech-srl/resources/pytech-django-tools
Project-URL: Bug Tracker, https://gitlab.com/pytech-srl/resources/pytech-django-tools/-/issues
Project-URL: Documentation, https://pytech-srl.gitlab.io/resources/pytech-django-tools/
Author-email: Alessandro Grandi <alessandro.grandi@pytech.it>
License-File: LICENCE
Classifier: License :: OSI Approved :: GNU Affero General Public License v3 or later (AGPLv3+)
Classifier: Operating System :: OS Independent
Classifier: Programming Language :: Python
Classifier: Programming Language :: Python :: 3
Requires-Python: >=3.6
Requires-Dist: django>=3
Requires-Dist: pytech-tools<3,>=2.0
